Metadata-Version: 2.4
Name: blendersynth
Version: 0.3.3
Summary: Synthetic Rendering for Blender
Author-email: Ollie Boyne <ollieboyne@gmail.com>
Project-URL: Homepage, https://github.com/OllieBoyne/BlenderSynth
License-File: LICENSE
Requires-Dist: platformdirs>=3.11.0
Requires-Dist: numpy
Requires-Dist: tqdm
Requires-Dist: ffmpeg-python
Requires-Dist: blender-stubs
Dynamic: license-file
